dfsql/__about__.py
dfsql/__init__.py
dfsql/cache.py
dfsql/commands.py
dfsql/config.py
dfsql/engine.py
dfsql/exceptions.py
dfsql/extensions.py
dfsql/functions.py
dfsql/table.py
dfsql/utils.py
dfsql/data_sources/__init__.py
dfsql/data_sources/base_data_source.py
dfsql-0.6.8.dist-info/LICENSE
dfsql-0.6.8.dist-info/METADATA
dfsql-0.6.8.dist-info/WHEEL
dfsql-0.6.8.dist-info/top_level.txt
dfsql-0.6.8.dist-info/RECORD
